jiffybox-0.11.0.dist-info/RECORD
jiffybox-0.11.0.dist-info/WHEEL
jiffybox-0.11.0.dist-info/metadata.json
jiffybox-0.11.0.dist-info/DESCRIPTION.rst
jiffybox-0.11.0.dist-info/METADATA
jiffybox-0.11.0.dist-info/entry_points.txt
jiffybox-0.11.0.dist-info/top_level.txt
jiffybox-0.11.0.dist-info/zip-safe
jiffybox/exceptions.py
jiffybox/cli.py
jiffybox/__init__.py
jiffybox/meta.py
jiffybox/format.py
jiffybox/api.py
