Metadata-Version: 2.0
Name: jiffybox
Version: 0.11.0
Summary: API wrapper for jiffybox.de
Home-page: https://github.com/AmadeusITGroup/python-jiffybox
Author: Thomas Weißschuh
Author-email: thomas.weissschuh@de.amadeus.com
License: GPL3
Keywords: API jiffybox domainfactory
Platform: UNKNOWN
Classifier: Development Status :: 4 - Beta
Classifier: Intended Audience :: Developers
Classifier: License :: OSI Approved :: GNU General Public License v3 (GPLv3)
Classifier: Operating System :: OS Independent
Classifier: Programming Language :: Python
Classifier: Topic :: Software Development :: Libraries :: Python Modules
Requires-Dist: requests
Requires-Dist: six
Provides-Extra: tests
Requires-Dist: pytest; extra == 'tests'
Requires-Dist: requests; extra == 'tests'
Requires-Dist: six; extra == 'tests'
Requires-Dist: click; extra == 'tests'
Requires-Dist: visitor (>=0.1.3); extra == 'tests'
Provides-Extra: cli
Requires-Dist: click; extra == 'cli'
Requires-Dist: visitor (>=0.1.3); extra == 'cli'
